{
    "openapi": "3.0.0",
    "info": {
        "title": "J Learning",
        "version": "0.1"
    },
    "paths": {
        "/api/v1/register": {
            "post": {
                "tags": [
                    "Auth"
                ],
                "description": "Register user",
                "operationId": "a5a8544276d0083b09928a02e698b6db",
                "requestBody": {
                    "content": {
                        "application/json": {
                            "schema": {
                                "properties": {
                                    "": {
                                        "properties": {
                                            "email": {
                                                "type": "string"
                                            },
                                            "password": {
                                                "type": "string"
                                            }
                                        },
                                        "type": "object"
                                    }
                                },
                                "type": "object",
                                "example": {
                                    "name": "My Name",
                                    "email": "email@example.com",
                                    "password": "123456"
                                }
                            }
                        }
                    }
                },
                "responses": {
                    "200": {
                        "description": "success",
                        "content": {
                            "application/json": {
                                "schema": {
                                    "properties": {
                                        "id": {
                                            "type": "number",
                                            "example": 1
                                        },
                                        "name": {
                                            "type": "string",
                                            "example": "My Name"
                                        },
                                        "email": {
                                            "type": "string",
                                            "example": "email@example.com"
                                        },
                                        "updated_at": {
                                            "type": "string",
                                            "example": "2021-12-11T09:25:53.000000Z"
                                        },
                                        "created_at": {
                                            "type": "string",
                                            "example": "2021-12-11T09:25:53.000000Z"
                                        }
                                    },
                                    "type": "object"
                                }
                            }
                        }
                    }
                }
            }
        }
    }
}